Metadata-Version: 2.1
Name: CythonProjectTemplate
Version: 0.1.0
Author-email: "Joe P. Renaud" <Joe.P.Renaud@gmail.com>
License: [CythonProjectTemplate]() © 2023 by [Joe P. Renaud]() is licensed under [Attribution 4.0 International](https://creativecommons.org/licenses/by/4.0).
Project-URL: Homepage, https://github.com/jrenaud90/CythonProjectTemplate
Project-URL: Bug Tracker, https://github.com/jrenaud90/CythonProjectTemplate/issues
Requires-Python: >=3.8
Provides-Extra: dev
License-File: LICENSE.md
